balancetwofunds.py
balancetwofunds-1.0.0.dist-info/LICENSE
balancetwofunds-1.0.0.dist-info/METADATA
balancetwofunds-1.0.0.dist-info/WHEEL
balancetwofunds-1.0.0.dist-info/entry_points.txt
balancetwofunds-1.0.0.dist-info/top_level.txt
balancetwofunds-1.0.0.dist-info/zip-safe
balancetwofunds-1.0.0.dist-info/RECORD
