Metadata-Version: 2.1
Name: balancetwofunds
Version: 1.0.0
Summary: A Python CLI that does the necessary math to balance two investment funds with a new deposit
Home-page: https://www.github.com/mattyoungberg/BalanceTwoFunds
Download-URL: https://www.github.com/mattyoungberg/BalanceTwoFunds/releases
Author: Matt Youngberg
Author-email: matt_youngberg@outlook.com
License: LICENSE
Platform: Cross-platform
Classifier: Development Status :: 5 - Production/Stable
Classifier: Environment :: Console
Classifier: Intended Audience :: Financial and Insurance Industry
Classifier: License :: OSI Approved :: MIT License
Classifier: Natural Language :: English
Classifier: Operating System :: OS Independent
Classifier: Programming Language :: Python :: 3.6
Classifier: Programming Language :: Python :: 3.7
Classifier: Programming Language :: Python :: 3.8
Classifier: Programming Language :: Python :: 3.9
Classifier: Programming Language :: Python :: 3.10
Classifier: Programming Language :: Python :: 3.11
Classifier: Topic :: Office/Business :: Financial
Classifier: Topic :: Office/Business :: Financial :: Investment
Classifier: Topic :: Software Development :: Libraries :: Python Modules
Classifier: Topic :: Software Development :: Version Control :: Git
Classifier: Typing :: Typed
Requires-Python: >=3.6.0
License-File: LICENSE
